FeiguaDataCollection/__init__.py
FeiguaDataCollection/_browser_utils.py
FeiguaDataCollection/_utils.py
FeiguaDataCollection/collector.py
FeiguaDataCollection/team_manage/_dict.py
FeiguaDataCollection/team_manage/_utils.py
FeiguaDataCollection/team_manage/anchor.py
FeiguaDataCollection/team_manage/team_manage.py
feigua_data_collection-1.0.1.dist-info/LICENSE
feigua_data_collection-1.0.1.dist-info/METADATA
feigua_data_collection-1.0.1.dist-info/WHEEL
feigua_data_collection-1.0.1.dist-info/RECORD
